{
	"configurations" : 
	[
		{
			"directories" : 
			[
				{
					"build" : ".",
					"jsonFile" : "directory-.-Debug-d0094a50bb2071803777.json",
					"minimumCMakeVersion" : 
					{
						"string" : "3.8"
					},
					"projectIndex" : 0,
					"source" : ".",
					"targetIndexes" : 
					[
						0
					]
				}
			],
			"name" : "Debug",
			"projects" : 
			[
				{
					"directoryIndexes" : 
					[
						0
					],
					"name" : "MetricsVK",
					"targetIndexes" : 
					[
						0
					]
				}
			],
			"targets" : 
			[
				{
					"directoryIndex" : 0,
					"id" : "MetricsVK::@6890427a1f51a3e7e1df",
					"jsonFile" : "target-MetricsVK-Debug-7b564898dcfb87e5ca07.json",
					"name" : "MetricsVK",
					"projectIndex" : 0
				}
			]
		}
	],
	"kind" : "codemodel",
	"paths" : 
	{
		"build" : "C:/Users/\u0415\u0433\u043e\u0440/\u0423\u0447\u0435\u0431\u0430/MetricsVK/out/build/x64-debug",
		"source" : "C:/Users/\u0415\u0433\u043e\u0440/\u0423\u0447\u0435\u0431\u0430/MetricsVK"
	},
	"version" : 
	{
		"major" : 2,
		"minor" : 7
	}
}
